[
    {
        "company": "Kunduz",
        "status": "Active",
        "industry": "Education, Training, & Coaching",
        "platform": "Wefunder",
        "valuation_cap": "$45,000,000",
        "security_type": "SAFE",
        "average_daily_raise": "$222",
        "amount_raised": "$102,926",
        "start_date": "04/02/21",
        "close_date": "05/01/23",
        "investors": "217",
        "reg_type": "TTW",
        "revenue": "",
        "source": "https://kingscrowd.com/kunduz-on-wefunder-2021/",
        "intermediary": "https://wefunder.com/kunduz/",
        "cover": "https://dfon51l7zffjj.cloudfront.net/uploads/company/header_media_photo/82372/standard_cropped_Screen_Shot_2021-03-23_at_5.18.31_PM.jpg"
    },
    {
        "company": "KK Technologies",
        "status": "Active",
        "industry": "Alcohol, Tobacco, & Recreational Drugs",
        "platform": "Wefunder",
        "valuation_cap": "$12,500,000",
        "security_type": "SAFE",
        "average_daily_raise": "$276",
        "amount_raised": "$71,975",
        "start_date": "10/22/21",
        "close_date": "05/01/23",
        "investors": "35",
        "reg_type": "RegCF",
        "revenue": "$0",
        "source": "https://kingscrowd.com/kk-technologies-on-wefunder-2021/",
        "intermediary": "https://wefunder.com/kushklubs/",
        "cover": "https://d2qbf73089ujv4.cloudfront.net/uploads/company/header_media_photo/84070/standard_cropped_REV_video_cover_image_.jpg"
    },
    {
        "company": "CIHC",
        "status": "Active",
        "industry": "Industrial Services",
        "platform": "Wefunder",
        "valuation_cap": "$32,000,000",
        "security_type": "SAFE",
        "average_daily_raise": "$5,200",
        "amount_raised": "$1,622,362",
        "start_date": "09/01/21",
        "close_date": "05/01/23",
        "investors": "-",
        "reg_type": "TTW",
        "revenue": "",
        "source": "https://kingscrowd.com/cihc-on-wefunder-2021/",
        "intermediary": "https://wefunder.com/cihc",
        "cover": "https://d2qbf73089ujv4.cloudfront.net/uploads/company/header_media_photo/90728/standard_cropped_1653936444687_ABMT_R_export.jpg"
    },
    {
        "company": "Sash Group",
        "status": "Active",
        "industry": "Apparel & Fashion",
        "platform": "Wefunder",
        "valuation_cap": "$10,000,000",
        "security_type": "SAFE",
        "average_daily_raise": "$1,590",
        "amount_raised": "$516,756",
        "start_date": "08/19/21",
        "close_date": "05/01/23",
        "investors": "58",
        "reg_type": "TTW",
        "revenue": "",
        "source": "https://kingscrowd.com/sash-group-on-wefunder-2021/",
        "intermediary": "https://wefunder.com/sashgroupinc",
        "cover": "https://dfon51l7zffjj.cloudfront.net/uploads/company/header_media_photo/77906/standard_cropped_NicholeBagsBackground.jpg"
    },
    {
        "company": "Tap Systems",
        "status": "Active",
        "industry": "Media, Entertainment & Publishing",
        "platform": "Wefunder",
        "valuation_cap": "$51,271,714",
        "security_type": "Equity - Common",
        "average_daily_raise": "$11,028",
        "amount_raised": "$2,723,869",
        "start_date": "11/05/21",
        "close_date": "05/01/23",
        "investors": "3,567",
        "reg_type": "RegCF",
        "revenue": "$885,346",
        "source": "https://kingscrowd.com/tap-systems-on-wefunder-2021/",
        "intermediary": "https://wefunder.com/tapwithus/",
        "cover": "https://d2qbf73089ujv4.cloudfront.net/uploads/company/header_media_photo/85271/standard_cropped_Wefunder-hero.jpg"
    },
    {
        "company": "Boxabl",
        "status": "Active",
        "industry": "Real Estate & Construction",
        "platform": "Republic",
        "valuation_cap": "$3,000,000,000",
        "security_type": "Equity - Preferred",
        "average_daily_raise": "$6,259",
        "amount_raised": "$625,873",
        "start_date": "04/01/22",
        "close_date": "04/02/25",
        "investors": "315",
        "reg_type": "RegA+",
        "revenue": "$90,000",
        "source": "https://kingscrowd.com/boxabl-on-republic-2022/",
        "intermediary": "https://republic.com/boxabl",
        "cover": "https://uploads.republic.com/p/offerings/seo_images/default/000/000/856/856-1614561554-ed9649f52971d83e396804b1e8e5fe6ccda45186.jpg"
    },
    {
        "company": "iMorph Smart Health Technologies",
        "status": "Active",
        "industry": "Healthcare & Pharmaceuticals",
        "platform": "Wefunder",
        "valuation_cap": "$22,000,000",
        "security_type": "Equity - Preferred",
        "average_daily_raise": "$452",
        "amount_raised": "$100,851",
        "start_date": "11/29/21",
        "close_date": "05/01/23",
        "investors": "32",
        "reg_type": "RegCF",
        "revenue": "$0",
        "source": "https://kingscrowd.com/imorph-smart-health-technologies-on-wefunder-2021/",
        "intermediary": "https://wefunder.com/imorphtechnologies/",
        "cover": "https://dfon51l7zffjj.cloudfront.net/uploads/company/header_media_photo/100337/standard_cropped_Web_capture_5-10-2021_122340_www.imorphed.com.jpg"
    },
    {
        "company": "Aro Lucha Animation & Entertainment",
        "status": "Active",
        "industry": "Media, Entertainment & Publishing",
        "platform": "Wefunder",
        "valuation_cap": "$3,152,330",
        "security_type": "Equity - Preferred",
        "average_daily_raise": "$1,483",
        "amount_raised": "$295,054",
        "start_date": "12/23/21",
        "close_date": "05/01/23",
        "investors": "546",
        "reg_type": "RegCF",
        "revenue": "$0",
        "source": "https://kingscrowd.com/aro-lucha-animation-entertainment-on-wefunder-2021/",
        "intermediary": "https://wefunder.com/arolucha/",
        "cover": "https://d2qbf73089ujv4.cloudfront.net/uploads/company/header_media_photo/22467/standard_cropped_image_6483441.jpg"
    },
    {
        "company": "Moxey",
        "status": "Active",
        "industry": "Financial & Insurance Products & Services",
        "platform": "Wefunder",
        "valuation_cap": "$15,167,460",
        "security_type": "Equity - Common",
        "average_daily_raise": "$754",
        "amount_raised": "$122,823",
        "start_date": "01/28/22",
        "close_date": "05/01/23",
        "investors": "140",
        "reg_type": "RegCF",
        "revenue": "$235,889",
        "source": "https://kingscrowd.com/moxey-on-wefunder-2022/",
        "intermediary": "https://wefunder.com/moxey/",
        "cover": "https://dfon51l7zffjj.cloudfront.net/uploads/company/header_media_photo/72663/standard_cropped_Moxey_Wefunder_Main.jpg"
    },
    {
        "company": "Swopblock",
        "status": "Active",
        "industry": "Financial & Insurance Products & Services",
        "platform": "Wefunder",
        "valuation_cap": "$3,500,000",
        "security_type": "SAFE",
        "average_daily_raise": "$1,683",
        "amount_raised": "$587,196",
        "start_date": "07/26/21",
        "close_date": "04/30/23",
        "investors": "747",
        "reg_type": "RegCF",
        "revenue": "$0",
        "source": "https://www.kingscrowd.com/swopblock-on-wefunder-2021/",
        "intermediary": "https://wefunder.com/swopblock/",
        "cover": "https://d2qbf73089ujv4.cloudfront.net/uploads/company/header_media_photo/75960/standard_cropped_VideoThumbnail_copy3.jpg"
    },
    {
        "company": "Power Panel",
        "status": "Active",
        "industry": "Energy, Power, & Natural Resources",
        "platform": "Wefunder",
        "valuation_cap": "$7,015,000",
        "security_type": "Equity - Common",
        "average_daily_raise": "$591",
        "amount_raised": "$222,195",
        "start_date": "06/29/21",
        "close_date": "05/01/23",
        "investors": "236",
        "reg_type": "RegCF",
        "revenue": "$7,030",
        "source": "https://www.kingscrowd.com/power-panel-on-wefunder-2021/",
        "intermediary": "https://wefunder.com/powerpanel/",
        "cover": "https://d2qbf73089ujv4.cloudfront.net/uploads/company/header_media_photo/79147/standard_cropped_xl_cropped_PP_Biz_Card_-_Back.Final.jpg"
    },
    {
        "company": "Pranos",
        "status": "Active",
        "industry": "Marketing & Advertising",
        "platform": "Wefunder",
        "valuation_cap": "$9,000,000",
        "security_type": "Convertible Note",
        "average_daily_raise": "$501",
        "amount_raised": "$155,906",
        "start_date": "09/02/21",
        "close_date": "04/30/23",
        "investors": "356",
        "reg_type": "RegCF",
        "revenue": "$2,322",
        "source": "https://kingscrowd.com/pranos-on-wefunder-2021/",
        "intermediary": "https://wefunder.com/pranosai/",
        "cover": "https://d2qbf73089ujv4.cloudfront.net/uploads/company/header_media_photo/75847/standard_cropped_sprinterHoloGlass.jpg"
    },
    {
        "company": "Espanita Tequila Company",
        "status": "Active",
        "industry": "Alcohol, Tobacco, & Recreational Drugs",
        "platform": "Wefunder",
        "valuation_cap": "$37,500,000",
        "security_type": "Equity - Preferred",
        "average_daily_raise": "-",
        "amount_raised": "-",
        "start_date": "10/11/21",
        "close_date": "04/30/23",
        "investors": "-",
        "reg_type": "RegCF",
        "revenue": "$0",
        "source": "https://kingscrowd.com/espanita-tequila-company-on-wefunder-2021/",
        "intermediary": "https://wefunder.com/espanitatequila/",
        "cover": "https://dfon51l7zffjj.cloudfront.net/uploads/company/header_media_photo/49683/standard_cropped_Landing_Image.jpg"
    },
    {
        "company": "The Yogi Trademark Movie",
        "status": "Active",
        "industry": "Media, Entertainment & Publishing",
        "platform": "Wefunder",
        "valuation_cap": "$0",
        "security_type": "Revenue Share",
        "average_daily_raise": "$140",
        "amount_raised": "$44,951",
        "start_date": "08/24/21",
        "close_date": "04/30/23",
        "investors": "-",
        "reg_type": "RegCF",
        "revenue": "$0",
        "source": "https://kingscrowd.com/the-yogi-trademark-movie-on-wefunder-2021/",
        "intermediary": "https://wefunder.com/theyogimovie/",
        "cover": "https://d2qbf73089ujv4.cloudfront.net/uploads/company/header_media_photo/41373/standard_cropped_yogi_mat_1280_2.jpg"
    },
    {
        "company": "Called Higher Studios",
        "status": "Active",
        "industry": "Media, Entertainment & Publishing",
        "platform": "Wefunder",
        "valuation_cap": "$18,014,776",
        "security_type": "Equity - Common",
        "average_daily_raise": "$1,494",
        "amount_raised": "$394,321",
        "start_date": "10/19/21",
        "close_date": "04/30/23",
        "investors": "863",
        "reg_type": "RegCF",
        "revenue": "$2,942",
        "source": "https://kingscrowd.com/called-higher-studios-on-wefunder-2021/",
        "intermediary": "https://wefunder.com/calledhigherstudios/",
        "cover": "https://d2qbf73089ujv4.cloudfront.net/uploads/company/header_media_photo/95691/standard_cropped_shutterstock_750796270.jpg"
    },
    {
        "company": "Learnie",
        "status": "Active",
        "industry": "Education, Training, & Coaching",
        "platform": "Wefunder",
        "valuation_cap": "$5,500,000",
        "security_type": "SAFE",
        "average_daily_raise": "$2,514",
        "amount_raised": "$279,099",
        "start_date": "03/21/22",
        "close_date": "05/01/23",
        "investors": "50",
        "reg_type": "RegCF",
        "revenue": "$0",
        "source": "https://kingscrowd.com/learnie-on-wefunder-2022/",
        "intermediary": "https://wefunder.com/learnie/",
        "cover": "https://d2qbf73089ujv4.cloudfront.net/uploads/company/header_media_photo/90516/standard_cropped_wefunder_website_graphic.jpg"
    },
    {
        "company": "Fanera",
        "status": "Active",
        "industry": "Media, Entertainment & Publishing",
        "platform": "Wefunder",
        "valuation_cap": "$4,500,000",
        "security_type": "Convertible Note",
        "average_daily_raise": "$746",
        "amount_raised": "$284,410",
        "start_date": "06/24/21",
        "close_date": "04/30/23",
        "investors": "67",
        "reg_type": "RegCF",
        "revenue": "$46,500",
        "source": "https://www.kingscrowd.com/fanera-on-wefunder-2021/",
        "intermediary": "https://wefunder.com/fanera/",
        "cover": "https://dfon51l7zffjj.cloudfront.net/uploads/company/header_media_photo/80023/standard_cropped_Thumbnail_1.jpg"
    },
    {
        "company": "Aphios Pharma",
        "status": "Active",
        "industry": "Healthcare & Pharmaceuticals",
        "platform": "Wefunder",
        "valuation_cap": "$71,000,000",
        "security_type": "SAFE",
        "average_daily_raise": "$336",
        "amount_raised": "$93,641",
        "start_date": "10/04/21",
        "close_date": "04/30/23",
        "investors": "79",
        "reg_type": "RegCF",
        "revenue": "$0",
        "source": "https://kingscrowd.com/aphios-pharma-on-wefunder-2021/",
        "intermediary": "https://wefunder.com/aphiospharmallc/",
        "cover": "https://d2qbf73089ujv4.cloudfront.net/uploads/company/header_media_photo/88217/standard_cropped_WeFunder_page__1_.jpg"
    },
    {
        "company": "Papa John\u2019s Central Europe",
        "status": "Active",
        "industry": "Food, Beverage, & Restaurants",
        "platform": "Wefunder",
        "valuation_cap": "$48,900,000",
        "security_type": "Equity - Common",
        "average_daily_raise": "$1,204",
        "amount_raised": "$323,978",
        "start_date": "10/14/21",
        "close_date": "04/30/23",
        "investors": "-",
        "reg_type": "RegCF",
        "revenue": "$59,063,000",
        "source": "https://kingscrowd.com/papa-johns-central-europe-on-wefunder-2021/",
        "intermediary": "https://wefunder.com/papajohnseurope/",
        "cover": "https://dfon51l7zffjj.cloudfront.net/uploads/company/header_media_photo/80817/standard_cropped_VIdeoThumbnailAlternatives_t1_v2d__1_.jpg"
    },
    {
        "company": "PADL",
        "status": "Active",
        "industry": "Consumer Products, Goods & Services",
        "platform": "Wefunder",
        "valuation_cap": "$24,970,000",
        "security_type": "Equity - Preferred",
        "average_daily_raise": "$921",
        "amount_raised": "$203,612",
        "start_date": "12/01/21",
        "close_date": "04/30/23",
        "investors": "175",
        "reg_type": "RegCF",
        "revenue": "$24,498",
        "source": "https://kingscrowd.com/padl-on-wefunder-2021/",
        "intermediary": "https://wefunder.com/padl/",
        "cover": "https://dfon51l7zffjj.cloudfront.net/uploads/company/header_media_photo/99229/standard_cropped_Untitled_design__4_.2.jpg"
    },
    {
        "company": "Pace Diagnostics",
        "status": "Active",
        "industry": "Healthcare & Pharmaceuticals",
        "platform": "Wefunder",
        "valuation_cap": "$20,000,000",
        "security_type": "SAFE",
        "average_daily_raise": "$758",
        "amount_raised": "$166,075",
        "start_date": "12/03/21",
        "close_date": "04/30/23",
        "investors": "113",
        "reg_type": "RegCF",
        "revenue": "$0",
        "source": "https://kingscrowd.com/pace-diagnostics-on-wefunder-2021/",
        "intermediary": "https://wefunder.com/pacediagnostics/",
        "cover": "https://dfon51l7zffjj.cloudfront.net/uploads/company/header_media_photo/81510/standard_cropped_Pace_team_wefunder_3a.jpg"
    },
    {
        "company": "Centers for Age Control",
        "status": "Active",
        "industry": "Healthcare & Pharmaceuticals",
        "platform": "Wefunder",
        "valuation_cap": "$12,000,000",
        "security_type": "SAFE",
        "average_daily_raise": "$245",
        "amount_raised": "$57,777",
        "start_date": "11/16/21",
        "close_date": "04/30/23",
        "investors": "100",
        "reg_type": "RegCF",
        "revenue": "$68,378",
        "source": "https://kingscrowd.com/centers-for-age-control-on-wefunder-2021/",
        "intermediary": "https://wefunder.com/agemeter/",
        "cover": "https://d2qbf73089ujv4.cloudfront.net/uploads/company/header_media_photo/84186/standard_cropped_AgeMeter_In_Use_20200106.jpg"
    },
    {
        "company": "WedFun App",
        "status": "Active",
        "industry": "Media, Entertainment & Publishing",
        "platform": "Wefunder",
        "valuation_cap": "$11,000,000",
        "security_type": "SAFE",
        "average_daily_raise": "$190",
        "amount_raised": "$47,585",
        "start_date": "11/01/21",
        "close_date": "04/30/23",
        "investors": "-",
        "reg_type": "RegCF",
        "revenue": "$0",
        "source": "https://kingscrowd.com/wedfun-app-on-wefunder-2021/",
        "intermediary": "https://wefunder.com/wedfunapp/",
        "cover": "https://dfon51l7zffjj.cloudfront.net/uploads/company/header_media_photo/84458/standard_cropped_whatiswedfun.jpg"
    },
    {
        "company": "TTC Oncology",
        "status": "Active",
        "industry": "Healthcare & Pharmaceuticals",
        "platform": "Wefunder",
        "valuation_cap": "$25,000,000",
        "security_type": "SAFE",
        "average_daily_raise": "$614",
        "amount_raised": "$132,700",
        "start_date": "12/06/21",
        "close_date": "04/30/23",
        "investors": "67",
        "reg_type": "RegCF",
        "revenue": "$0",
        "source": "https://kingscrowd.com/ttc-oncology-on-wefunder-2021/",
        "intermediary": "https://wefunder.com/ttconcology/",
        "cover": "https://d2qbf73089ujv4.cloudfront.net/uploads/company/custom_card_photo/73530/large_cropped_TTC-352_capsules_WeFunder.jpg"
    },
    {
        "company": "The Tale of Nicky Newark",
        "status": "Active",
        "industry": "Media, Entertainment & Publishing",
        "platform": "Wefunder",
        "valuation_cap": "$0",
        "security_type": "Revenue Share",
        "average_daily_raise": "$299",
        "amount_raised": "$59,550",
        "start_date": "12/23/21",
        "close_date": "04/30/23",
        "investors": "-",
        "reg_type": "RegCF",
        "revenue": "",
        "source": "https://kingscrowd.com/the-tale-of-nicky-newark-on-wefunder-2021/",
        "intermediary": "",
        "cover": ""
    },
    {
        "company": "Vehiko",
        "status": "Active",
        "industry": "Consumer Products, Goods & Services",
        "platform": "Wefunder",
        "valuation_cap": "$8,000,000",
        "security_type": "SAFE",
        "average_daily_raise": "$552",
        "amount_raised": "$102,210",
        "start_date": "01/06/22",
        "close_date": "04/30/23",
        "investors": "-",
        "reg_type": "RegCF",
        "revenue": "$0",
        "source": "https://kingscrowd.com/vehiko-on-wefunder-2022/",
        "intermediary": "https://wefunder.com/vehiko/",
        "cover": "https://d2qbf73089ujv4.cloudfront.net/uploads/company/header_media_photo/94716/standard_cropped_Vehiko.jpg"
    },
    {
        "company": "RAD AI",
        "status": "Active",
        "industry": "Business Services, Software, & Applications",
        "platform": "Wefunder",
        "valuation_cap": "$18,000,812",
        "security_type": "Equity - Common",
        "average_daily_raise": "$8,454",
        "amount_raised": "$1,555,494",
        "start_date": "01/07/22",
        "close_date": "04/30/23",
        "investors": "1,445",
        "reg_type": "RegCF",
        "revenue": "",
        "source": "https://kingscrowd.com/rad-ai-on-wefunder-2022/",
        "intermediary": "",
        "cover": ""
    },
    {
        "company": "ReelwUrld",
        "status": "Active",
        "industry": "Media, Entertainment & Publishing",
        "platform": "Wefunder",
        "valuation_cap": "$10,700,000",
        "security_type": "Equity - Preferred",
        "average_daily_raise": "$305",
        "amount_raised": "$67,180",
        "start_date": "12/02/21",
        "close_date": "04/30/23",
        "investors": "34",
        "reg_type": "RegCF",
        "revenue": "$0",
        "source": "https://kingscrowd.com/reelwurld-on-wefunder-2021/",
        "intermediary": "https://wefunder.com/reelwurld/",
        "cover": "https://dfon51l7zffjj.cloudfront.net/uploads/company/header_media_photo/79986/standard_cropped_JanLucanus_ThaisAquinoPhotography41614.jpg"
    },
    {
        "company": "Parknav",
        "status": "Active",
        "industry": "Transportation, Automotive, Aviation, & Aerospace",
        "platform": "Wefunder",
        "valuation_cap": "$80,044,284",
        "security_type": "Equity - Preferred",
        "average_daily_raise": "$2,058",
        "amount_raised": "$450,739",
        "start_date": "12/03/21",
        "close_date": "04/30/23",
        "investors": "254",
        "reg_type": "RegCF",
        "revenue": "$521,796",
        "source": "https://kingscrowd.com/parknav-on-wefunder-2021/",
        "intermediary": "https://wefunder.com/parknav/",
        "cover": "https://d2qbf73089ujv4.cloudfront.net/uploads/company/header_media_photo/8730/standard_cropped_WF_video_thumbnail__1_.jpg"
    },
    {
        "company": "Boseco",
        "status": "Active",
        "industry": "Food, Beverage, & Restaurants",
        "platform": "Wefunder",
        "valuation_cap": "$9,000,000",
        "security_type": "SAFE",
        "average_daily_raise": "$3,658",
        "amount_raised": "$662,112",
        "start_date": "01/10/22",
        "close_date": "04/30/23",
        "investors": "310",
        "reg_type": "RegCF",
        "revenue": "$150,916",
        "source": "https://kingscrowd.com/boseco-on-wefunder-2022/",
        "intermediary": "https://wefunder.com/boseco/",
        "cover": "https://d2qbf73089ujv4.cloudfront.net/uploads/company/header_media_photo/102176/standard_cropped_bikebigimg.jpg"
    },
    {
        "company": "Doodeo",
        "status": "Active",
        "industry": "Consumer Products, Goods & Services",
        "platform": "Wefunder",
        "valuation_cap": "$12,000,000",
        "security_type": "SAFE",
        "average_daily_raise": "-",
        "amount_raised": "-",
        "start_date": "01/31/22",
        "close_date": "04/30/23",
        "investors": "-",
        "reg_type": "RegCF",
        "revenue": "",
        "source": "https://kingscrowd.com/doodeo-on-wefunder-2022/",
        "intermediary": "",
        "cover": ""
    },
    {
        "company": "Armslock USA",
        "status": "Active",
        "industry": "Security, Cybersecurity, & Defense",
        "platform": "Wefunder",
        "valuation_cap": "$11,549,250",
        "security_type": "Equity - Preferred",
        "average_daily_raise": "$456",
        "amount_raised": "$106,782",
        "start_date": "11/18/21",
        "close_date": "04/30/23",
        "investors": "55",
        "reg_type": "RegCF",
        "revenue": "$0",
        "source": "https://kingscrowd.com/armslock-usa-on-wefunder-2021/",
        "intermediary": "https://wefunder.com/armslockusa/",
        "cover": "https://d2qbf73089ujv4.cloudfront.net/uploads/company/header_media_photo/71740/standard_cropped_xl_cropped_campaign_photo_5.jpg"
    },
    {
        "company": "SkyGoal",
        "status": "Active",
        "industry": "Education, Training, & Coaching",
        "platform": "Wefunder",
        "valuation_cap": "$5,000,000",
        "security_type": "SAFE",
        "average_daily_raise": "$0",
        "amount_raised": "-",
        "start_date": "01/13/22",
        "close_date": "04/30/23",
        "investors": "-",
        "reg_type": "RegCF",
        "revenue": "",
        "source": "https://kingscrowd.com/skygoal-on-wefunder-2022/",
        "intermediary": "",
        "cover": ""
    },
    {
        "company": "ABC Fintech",
        "status": "Active",
        "industry": "Real Estate & Construction",
        "platform": "Wefunder",
        "valuation_cap": "$42,350,000",
        "security_type": "Equity - Preferred",
        "average_daily_raise": "$2,122",
        "amount_raised": "$330,997",
        "start_date": "02/04/22",
        "close_date": "04/30/23",
        "investors": "297",
        "reg_type": "RegCF",
        "revenue": "",
        "source": "https://kingscrowd.com/abc-fintech-on-wefunder-2022/",
        "intermediary": "",
        "cover": ""
    },
    {
        "company": "GroGuru",
        "status": "Active",
        "industry": "Farming & Agriculture",
        "platform": "Wefunder",
        "valuation_cap": "$14,716,316",
        "security_type": "Equity - Preferred",
        "average_daily_raise": "$3,114",
        "amount_raised": "$476,445",
        "start_date": "02/07/22",
        "close_date": "04/30/23",
        "investors": "357",
        "reg_type": "RegCF",
        "revenue": "",
        "source": "https://kingscrowd.com/groguru-on-wefunder-2022/",
        "intermediary": "",
        "cover": ""
    },
    {
        "company": "Buttonsmith",
        "status": "Active",
        "industry": "Industrial Services",
        "platform": "Wefunder",
        "valuation_cap": "$24,999,597",
        "security_type": "Equity - Preferred",
        "average_daily_raise": "$4,425",
        "amount_raised": "$787,665",
        "start_date": "01/13/22",
        "close_date": "04/30/23",
        "investors": "519",
        "reg_type": "RegCF",
        "revenue": "$5,522,792",
        "source": "https://kingscrowd.com/buttonsmith-on-wefunder-2022/",
        "intermediary": "https://wefunder.com/buttonsmithinc/",
        "cover": "https://d2qbf73089ujv4.cloudfront.net/uploads/company/header_media_photo/82277/standard_cropped_Screen_Shot_2022-02-16_at_11.30.13_AM.jpg"
    },
    {
        "company": "Riff",
        "status": "Active",
        "industry": "Food, Beverage, & Restaurants",
        "platform": "Wefunder",
        "valuation_cap": "$11,075,564",
        "security_type": "Equity - Preferred",
        "average_daily_raise": "$2,240",
        "amount_raised": "$396,545",
        "start_date": "01/14/22",
        "close_date": "04/30/23",
        "investors": "208",
        "reg_type": "RegCF",
        "revenue": "$414,316",
        "source": "https://kingscrowd.com/riff-on-wefunder-2022/",
        "intermediary": "https://wefunder.com/letsriff/",
        "cover": "https://d2qbf73089ujv4.cloudfront.net/uploads/company/header_media_photo/96892/standard_cropped_RIFF-Wefunder-video-still-2.jpg"
    },
    {
        "company": "Cohere",
        "status": "Active",
        "industry": "Real Estate & Construction",
        "platform": "Wefunder",
        "valuation_cap": "$5,500,000",
        "security_type": "SAFE",
        "average_daily_raise": "$776",
        "amount_raised": "$131,838",
        "start_date": "01/21/22",
        "close_date": "04/30/23",
        "investors": "127",
        "reg_type": "RegCF",
        "revenue": "$0",
        "source": "https://kingscrowd.com/cohere-on-wefunder-2022/",
        "intermediary": "https://wefunder.com/cohere/",
        "cover": "https://d2qbf73089ujv4.cloudfront.net/uploads/company/header_media_photo/101635/standard_cropped_EQUITY__Wefunder_.jpg"
    },
    {
        "company": "Next Bolt",
        "status": "Active",
        "industry": "Energy, Power, & Natural Resources",
        "platform": "Wefunder",
        "valuation_cap": "$35,120,002",
        "security_type": "Equity - Preferred",
        "average_daily_raise": "$21,472",
        "amount_raised": "$3,134,853",
        "start_date": "02/14/22",
        "close_date": "04/30/23",
        "investors": "3,900",
        "reg_type": "RegCF",
        "revenue": "$0",
        "source": "https://kingscrowd.com/next-bolt-on-wefunder-2022/",
        "intermediary": "https://wefunder.com/nextbolt/",
        "cover": "https://dfon51l7zffjj.cloudfront.net/uploads/company/header_media_photo/72352/standard_cropped_Watch_this_video_first___1_.jpg"
    },
    {
        "company": "Just A Baby",
        "status": "Active",
        "industry": "Media, Entertainment & Publishing",
        "platform": "Wefunder",
        "valuation_cap": "$12,000,000",
        "security_type": "Equity - Preferred",
        "average_daily_raise": "$1,058",
        "amount_raised": "$151,250",
        "start_date": "02/17/22",
        "close_date": "04/30/23",
        "investors": "311",
        "reg_type": "RegCF",
        "revenue": "$91,132",
        "source": "https://kingscrowd.com/just-a-baby-on-wefunder-2022/",
        "intermediary": "https://wefunder.com/justababy/",
        "cover": "https://d2qbf73089ujv4.cloudfront.net/uploads/company/header_media_photo/88745/standard_cropped_FbCoverV3.jpg"
    },
    {
        "company": "PeerKnect",
        "status": "Active",
        "industry": "Media, Entertainment & Publishing",
        "platform": "Wefunder",
        "valuation_cap": "$4,000,000",
        "security_type": "SAFE",
        "average_daily_raise": "$384",
        "amount_raised": "$54,575",
        "start_date": "02/18/22",
        "close_date": "04/30/23",
        "investors": "-",
        "reg_type": "RegCF",
        "revenue": "$311",
        "source": "https://kingscrowd.com/peerknect-on-wefunder-2022/",
        "intermediary": "https://wefunder.com/peerknect/",
        "cover": "https://d2qbf73089ujv4.cloudfront.net/uploads/company/header_media_photo/104697/standard_cropped_Demo_For_Parents-4.jpg"
    },
    {
        "company": "necoTECH",
        "status": "Active",
        "industry": "Real Estate & Construction",
        "platform": "Wefunder",
        "valuation_cap": "$25,000,000",
        "security_type": "SAFE",
        "average_daily_raise": "$1,350",
        "amount_raised": "$203,818",
        "start_date": "02/09/22",
        "close_date": "04/30/23",
        "investors": "169",
        "reg_type": "RegCF",
        "revenue": "$2,000,000",
        "source": "https://kingscrowd.com/necotech-on-wefunder-2022/",
        "intermediary": "https://wefunder.com/necotech/",
        "cover": "https://dfon51l7zffjj.cloudfront.net/uploads/company/header_media_photo/89672/standard_cropped_necoTech_WeFunder_Hero_Image_cropped.jpg"
    }
]